ckanext_dcor_theme-1.1.4-py3.12-nspkg.pth
ckanext/dcor_theme/.gitignore
ckanext/dcor_theme/__init__.py
ckanext/dcor_theme/_version.py
ckanext/dcor_theme/plugin.py
ckanext/dcor_theme/assets/hide_action_buttons.css
ckanext/dcor_theme/assets/webassets.yml
ckanext/dcor_theme/assets_theme/.gitignore
ckanext/dcor_theme/assets_theme/webassets.yml
ckanext/dcor_theme/cli/__init__.py
ckanext/dcor_theme/cli/i18n_branding.py
ckanext/dcor_theme/cli/main_css_branding.py
ckanext/dcor_theme/cli/patch_ckan_templates.py
ckanext/dcor_theme/css/README.md
ckanext/dcor_theme/css/__init__.py
ckanext/dcor_theme/css/dcor_theme.css
ckanext/dcor_theme/css/lato_fonts.css
ckanext/dcor_theme/css/make_dcor_main_css.py
ckanext/dcor_theme/public/.gitignore
ckanext/dcor_theme/public/favicon.svg
ckanext/dcor_theme/public/generate_icons.sh
ckanext/dcor_theme/public/base/images/background-tile.png
ckanext/dcor_theme/public/base/images/ckan-logo.png
ckanext/dcor_theme/public/base/images/ckan-logo.svg
ckanext/dcor_theme/public/base/images/placeholder-group.png
ckanext/dcor_theme/public/base/images/placeholder-group.svg
ckanext/dcor_theme/public/base/images/placeholder-organization.png
ckanext/dcor_theme/public/base/images/placeholder-organization.svg
ckanext/dcor_theme/public/fonts/Lato-Bold.eot
ckanext/dcor_theme/public/fonts/Lato-Bold.ttf
ckanext/dcor_theme/public/fonts/Lato-Bold.woff
ckanext/dcor_theme/public/fonts/Lato-Bold.woff2
ckanext/dcor_theme/public/fonts/Lato-BoldItalic.eot
ckanext/dcor_theme/public/fonts/Lato-BoldItalic.ttf
ckanext/dcor_theme/public/fonts/Lato-BoldItalic.woff
ckanext/dcor_theme/public/fonts/Lato-BoldItalic.woff2
ckanext/dcor_theme/public/fonts/Lato-Italic.eot
ckanext/dcor_theme/public/fonts/Lato-Italic.ttf
ckanext/dcor_theme/public/fonts/Lato-Italic.woff
ckanext/dcor_theme/public/fonts/Lato-Italic.woff2
ckanext/dcor_theme/public/fonts/Lato-Regular.eot
ckanext/dcor_theme/public/fonts/Lato-Regular.ttf
ckanext/dcor_theme/public/fonts/Lato-Regular.woff
ckanext_dcor_theme-1.1.4.dist-info/licenses/LICENSE
ckanext_dcor_theme-1.1.4.dist-info/METADATA
ckanext_dcor_theme-1.1.4.dist-info/WHEEL
ckanext_dcor_theme-1.1.4.dist-info/entry_points.txt
ckanext_dcor_theme-1.1.4.dist-info/namespace_packages.txt
ckanext_dcor_theme-1.1.4.dist-info/top_level.txt
ckanext_dcor_theme-1.1.4.dist-info/RECORD
