Metadata-Version: 2.4
Name: ckanext-dcor_theme
Version: 1.1.4
Summary: The DCOR CKAN theme
Author: Paul Müller
Maintainer-email: Paul Müller <dev@craban.de>
License: GNU Affero General Public License v3 or later (AGPLv3+)
Project-URL: source, https://github.com/DCOR-dev/ckanext-dcor_theme
Project-URL: tracker, https://github.com/DCOR-dev/ckanext-dcor_theme/issues
Project-URL: changelog, https://github.com/DCOR-dev/ckanext-dcor_theme/blob/main/CHANGELOG
Keywords: DC,DCOR,deformability,cytometry
Classifier: Operating System :: OS Independent
Classifier: Programming Language :: Python :: 3
Classifier: Topic :: Scientific/Engineering :: Visualization
Classifier: Intended Audience :: Science/Research
Requires-Python: <4,>=3.8
License-File: LICENSE
Requires-Dist: ckan<3,>=2.10.4
Requires-Dist: Babel>=2.8.0
Dynamic: license-file
